MANIFEST.in
README.rst
setup.py
acrylamid/__init__.py
acrylamid/assets.py
acrylamid/colors.py
acrylamid/commands.py
acrylamid/conf.py
acrylamid/core.py
acrylamid/errors.py
acrylamid/helpers.py
acrylamid/hooks.py
acrylamid/log.py
acrylamid/readers.py
acrylamid/refs.py
acrylamid/utils.py
acrylamid.egg-info/PKG-INFO
acrylamid.egg-info/SOURCES.txt
acrylamid.egg-info/dependency_links.txt
acrylamid.egg-info/entry_points.txt
acrylamid.egg-info/not-zip-safe
acrylamid.egg-info/requires.txt
acrylamid.egg-info/top_level.txt
acrylamid/defaults/__init__.py
acrylamid/defaults/conf.py
acrylamid/defaults/sample-entry.txt
acrylamid/defaults/html5/__init__.py
acrylamid/defaults/html5/style.css
acrylamid/defaults/html5/jinja2/articles.html
acrylamid/defaults/html5/jinja2/base.html
acrylamid/defaults/html5/jinja2/entry.html
acrylamid/defaults/html5/jinja2/main.html
acrylamid/defaults/html5/mako/articles.html
acrylamid/defaults/html5/mako/base.html
acrylamid/defaults/html5/mako/entry.html
acrylamid/defaults/html5/mako/main.html
acrylamid/defaults/jinja2/atom.xml
acrylamid/defaults/jinja2/rss.xml
acrylamid/defaults/mako/atom.xml
acrylamid/defaults/mako/rss.xml
acrylamid/defaults/shadowplay/jinja2/__init__.py
acrylamid/defaults/shadowplay/jinja2/articles.html
acrylamid/defaults/shadowplay/jinja2/base.html
acrylamid/defaults/shadowplay/jinja2/conf.py
acrylamid/defaults/shadowplay/jinja2/entry.html
acrylamid/defaults/shadowplay/jinja2/main.html
acrylamid/defaults/shadowplay/jinja2/shadowplay.css
acrylamid/defaults/shadowplay/jinja2/content/about.txt
acrylamid/defaults/shadowplay/jinja2/content/ipsum.txt
acrylamid/defaults/shadowplay/jinja2/content/lorem.txt
acrylamid/defaults/shadowplay/jinja2/content/shadowplay.txt
acrylamid/defaults/shadowplay/jinja2/img/arrow.png
acrylamid/defaults/shadowplay/jinja2/img/back.png
acrylamid/defaults/shadowplay/jinja2/img/link.png
acrylamid/defaults/shadowplay/jinja2/img/logo.png
acrylamid/filters/__init__.py
acrylamid/filters/acronyms.py
acrylamid/filters/head_offset.py
acrylamid/filters/html.py
acrylamid/filters/hyphenation.py
acrylamid/filters/intro.py
acrylamid/filters/jinja2-templating.py
acrylamid/filters/mako-templating.py
acrylamid/filters/md.py
